torchdtcc/__init__.py
torchdtcc/augmentations/__init__.py
torchdtcc/augmentations/basic.py
torchdtcc/augmentations/dtw.py
torchdtcc/augmentations/helper.py
torchdtcc/augmentations/label_dependent.py
torchdtcc/datasets/__init__.py
torchdtcc/datasets/augmented_dataset.py
torchdtcc/datasets/fuglmeyer/__init__.py
torchdtcc/datasets/meat/__init__.py
torchdtcc/datasets/meat/arff_meat.py
torchdtcc/datasets/meat/arff_plane.py
torchdtcc/dtcc/__init__.py
torchdtcc/dtcc/clustering.py
torchdtcc/dtcc/dtcc.py
torchdtcc/dtcc/helper.py
torchdtcc/training/hyperparam_search.py
torchdtcc/training/metrics.py
torchdtcc/training/mlflow.py
torchdtcc/training/trainer.py
torchdtcc-0.0.7.dist-info/licenses/LICENSE
torchdtcc-0.0.7.dist-info/METADATA
torchdtcc-0.0.7.dist-info/WHEEL
torchdtcc-0.0.7.dist-info/top_level.txt
torchdtcc-0.0.7.dist-info/RECORD
