Metadata-Version: 2.4
Name: torchdtcc
Version: 0.0.7
Summary: Deep Temporal Contrastive Clustering for time series
Author-email: Zsombor Kalotay <zsombor.kalotay@gmail.ch>
License: MIT
Requires-Python: >=3.7
License-File: LICENSE
Requires-Dist: torch>=1.8
Requires-Dist: numpy>=1.19
Requires-Dist: tslearn>=0.5.2
Requires-Dist: scikit-learn>=0.22
Requires-Dist: tqdm>=4.45
Requires-Dist: pyyaml>=5.1
Requires-Dist: scipy>=1.5
Requires-Dist: pandas>=1.3.0
Requires-Dist: mlflow>=2.3.0
Provides-Extra: dev
Requires-Dist: jupyter; extra == "dev"
Requires-Dist: pytest; extra == "dev"
Requires-Dist: black; extra == "dev"
Requires-Dist: flake8; extra == "dev"
Dynamic: license-file
